{
  "type": "Feature",
  "stac_version": "1.0.0",
  "id": "elevation",
  "properties": {
    "title": "\"South-West Wake county: Elevation NED 10m\"",
    "description": "\"generated by r.proj\"",
    "proj:epsg": 3358,
    "grass:datatype": "FCELL",
    "grass:comments": "\"r.proj input=\"ned03arcsec\" location=\"northcarolina_latlong\" mapset=\"\\helena\" output=\"elev_ned10m\" method=\"cubic\" resolution=10\"",
    "grass:creator": "\"helena\"",
    "grass:ewres": "10",
    "grass:nsres": "10",
    "grass:cols": "1500",
    "grass:location": "nc_spm_08",
    "grass:mapset": "PERMANENT",
    "grass:map": "elevation",
    "grass:maptype": "raster",
    "grass:min": "55.57879",
    "grass:max": "156.3299",
    "grass:ncats": "255",
    "grass:semantic_label": "\"none\"",
    "grass:source1": "\"\"",
    "grass:source2": "\"\"",
    "datetime": "2006-07-11T01:09:51Z"
  },
  "geometry": {
    "type": "Polygon",
    "coordinates": [
      [
        [
          645000.0,
          215000.0
        ],
        [
          645000.0,
          228500.0
        ],
        [
          630000.0,
          228500.0
        ],
        [
          630000.0,
          215000.0
        ],
        [
          645000.0,
          215000.0
        ]
      ]
    ]
  },
  "links": [
    {
      "rel": "root",
      "href": "/home/coreywhite/Documents/GitHub/TomorrowNow/TomorrowNowApp/notebooks/grass_catalog/catalog.json",
      "type": "application/json"
    },
    {
      "rel": "collection",
      "href": "/home/coreywhite/Documents/GitHub/TomorrowNow/TomorrowNowApp/notebooks/grass_catalog/nc_spm_08/PERMANENT/collection.json",
      "type": "application/json",
      "title": "PERMANENT"
    },
    {
      "rel": "parent",
      "href": "/home/coreywhite/Documents/GitHub/TomorrowNow/TomorrowNowApp/notebooks/grass_catalog/nc_spm_08/PERMANENT/collection.json",
      "type": "application/json",
      "title": "PERMANENT"
    }
  ],
  "assets": {
    "raster": {
      "href": "/api/v3/locations/nc_spm_08/mapsets/PERMANENT/raster_layers/elevation",
      "type": "image/tiff; application=geotiff; profile=cloud-optimized",
      "title": "\"South-West Wake county: Elevation NED 10m\"",
      "roles": [
        "data"
      ]
    },
    "thumbnail": {
      "href": "/api/v3/locations/nc_spm_08/mapsets/PERMANENT/raster_layers/elevationrender",
      "type": "image/png",
      "title": "\"South-West Wake county: Elevation NED 10m\" Thumbnail",
      "roles": [
        "thumbnail"
      ]
    }
  },
  "bbox": [
    630000,
    215000,
    645000,
    228500
  ],
  "stac_extensions": [],
  "collection": "PERMANENT"
}